{
	"next_comment_id": 3,
	"comment": [
		{
			"comment_id": 1,
			"body": "3 in first line - the most balanced. (say as designer)\nand  2 in second line is better if you want be more unified (if you see later your project as a platform (or network protocol) for different developers, not only a one-side project)\n\nSorry for English, bcs im Russian.",
			"post_id": 56,
			"date_added": 1443875253
		},
		{
			"comment_id": 2,
			"body": "And ofcourse you dont need to match the hexogram and circle in top right corner, because it willbe not good looking. need to change a shape of a button\n",
			"post_id": 56,
			"date_added": 1444114824
		}
	],
	"comment_vote": {}
}