{
	"next_post_id": 4,
	"next_comment_id": 2,
	"next_follow_id": 1,
	"avatar": "generate",
	"user_name": "Decret",
	"hub": "1oranGeS2xsKZ4jVsu9SVttzgkYXu4k9v",
	"intro": "新 ZeroNet 用户",
	"post": [
		{
			"post_id": 1,
			"date_added": 1491125918,
			"body": "你好 ZeroMe!"
		},
		{
			"post_id": 1491125975,
			"body": "这个社交是怎么个交法？",
			"date_added": 1491125973
		},
		{
			"post_id": 1494418334,
			"body": "开车的不多，反动的不少，长者要万万岁了。+1s",
			"date_added": 1494418331
		}
	],
	"post_like": {},
	"comment": [
		{
			"comment_id": 1,
			"body": "@公共: 讲了个黄段子结果没人明白，是我太含蓄还是你们太纯洁",
			"post_uri": "1BGf8Eh2uJiPr52hvPUwQgKN5QUjgBM1Ai_1491125975",
			"date_added": 1491142730
		}
	],
	"follow": []
}