{
	"next_post_id": 4,
	"next_comment_id": 3,
	"next_follow_id": 4,
	"avatar": "generate",
	"user_name": "Nulledroot",
	"hub": "1oranGeS2xsKZ4jVsu9SVttzgkYXu4k9v",
	"intro": "Random ZeroNet user",
	"post": [
		{
			"post_id": 1,
			"date_added": 1489479999,
			"body": "Hello ZeroMe!"
		},
		{
			"post_id": 1489480209,
			"body": "nah",
			"date_added": 1489480207
		},
		{
			"post_id": 1489480275,
			"body": "so is this like twitter for ZeroNet?",
			"date_added": 1489480272
		}
	],
	"post_like": {
		"1FLjMvHZ4xhxCPR6vvHg2QJUTZJebwZxim_1489472317": 1489480240,
		"1FLjMvHZ4xhxCPR6vvHg2QJUTZJebwZxim_1489519679": 1489645956
	},
	"comment": [
		{
			"comment_id": 1,
			"body": "@Yinyue: ok also make your music site support multiple files (ill flood it for you)",
			"post_uri": "1Aa63ifDFsoYUZD4AtD7Dsm2JQrG6Stret_1489480275",
			"date_added": 1489481071
		},
		{
			"comment_id": 2,
			"body": "@Yinyue: ok",
			"post_uri": "1Aa63ifDFsoYUZD4AtD7Dsm2JQrG6Stret_1489480275",
			"date_added": 1489481681
		}
	],
	"follow": [
		{
			"follow_id": 2,
			"hub": "1oranGeS2xsKZ4jVsu9SVttzgkYXu4k9v",
			"auth_address": "1FLjMvHZ4xhxCPR6vvHg2QJUTZJebwZxim",
			"user_name": "Rek",
			"date_added": 1489480242
		},
		{
			"follow_id": 3,
			"hub": "1ABFCaadiEa3bFNzN3RcCZSsviqMNTbz3m",
			"auth_address": "1GNgaj5EqkzqYECYbXa889fGLyuseHRi3t",
			"user_name": "Yinyue",
			"date_added": 1489481079
		}
	]
}