{
	"next_post_id": 2,
	"next_comment_id": 1,
	"next_follow_id": 8,
	"avatar": "generate",
	"user_name": "854c741f2ba98652",
	"hub": "1RedkCkVaXuVXrqCMpoXQS29bwaqsuFdL",
	"intro": "新 ZeroNet 用户",
	"post": [
		{
			"post_id": 1,
			"date_added": 1491336676,
			"body": "你好 ZeroMe!"
		}
	],
	"post_like": {},
	"comment": [],
	"follow": [
		{
			"follow_id": 2,
			"hub": "1RedkCkVaXuVXrqCMpoXQS29bwaqsuFdL",
			"auth_address": "1LDgXnrcgeJqgPYdp6aW4T28C6RFuJZDxU",
			"user_name": "操GFW",
			"date_added": 1491336726
		},
		{
			"follow_id": 3,
			"hub": "1RedkCkVaXuVXrqCMpoXQS29bwaqsuFdL",
			"auth_address": "13Z7XxTa7JuFat3KzzMWu3onwM6biLuurJ",
			"user_name": "P2P",
			"date_added": 1491336738
		},
		{
			"follow_id": 4,
			"hub": "1RedkCkVaXuVXrqCMpoXQS29bwaqsuFdL",
			"auth_address": "1958F7oCppj78MP966AfojMQwHg2WUupzq",
			"user_name": "Lmath",
			"date_added": 1491336746
		},
		{
			"follow_id": 5,
			"hub": "1KNmG5rJUGhgUJGFbLkv2B5isaqu9PrZqi",
			"auth_address": "12Hk16Cbxe4WeH12HziJ8TWLpTbXvJJduX",
			"user_name": "Twister，自由的龙卷风",
			"date_added": 1491336756
		},
		{
			"follow_id": 6,
			"hub": "1RedkCkVaXuVXrqCMpoXQS29bwaqsuFdL",
			"auth_address": "1HNy2FfEu2g14HpkGjW68t3s5AXovN7iFF",
			"user_name": "Wenmingzhang27",
			"date_added": 1491336790
		},
		{
			"follow_id": 7,
			"hub": "1RedkCkVaXuVXrqCMpoXQS29bwaqsuFdL",
			"auth_address": "13jL799v8v688HkkF9nAVAse9PcieWBfVA",
			"user_name": "知乎日报",
			"date_added": 1491357178
		}
	]
}