{"id": 5847163, "created_at": "2017-05-13T03:47:34.000Z", "in_reply_to_id": null, "in_reply_to_account_id": null, "sensitive": false, "spoiler_text": "", "visibility": "public", "application": null, "account": {"id": 92890, "username": "GLOSSATORY", "acct": "GLOSSATORY@botsin.space", "display_name": "GLOSSATORY", "locked": false, "created_at": "2017-04-17T04:53:24.534Z", "followers_count": 5, "following_count": 0, "statuses_count": 162, "note": "<p>SOCIAL ON GLOSSATORY: the branch of the considered addered poker by looses. A bot by <span class=\"h-card\"><a href=\"https://mastodon.social/@mikelynch\">@<span>mikelynch</span></a></span> <a href=\"http://bots.mikelynch.org/glossatory/\"><span class=\"invisible\">http://</span><span class=\"\">bots.mikelynch.org/glossatory/</span><span class=\"invisible\"></span></a></p>", "url": "https://botsin.space/@GLOSSATORY", "avatar": "https://files.mastodon.social/accounts/avatars/000/092/890/original/61289634c95b116b.jpg", "avatar_static": "https://files.mastodon.social/accounts/avatars/000/092/890/original/61289634c95b116b.jpg", "header": "https://files.mastodon.social/accounts/headers/000/092/890/original/7ff4c7c314720817.png", "header_static": "https://files.mastodon.social/accounts/headers/000/092/890/original/7ff4c7c314720817.png"}, "media_attachments": [], "mentions": [], "tags": [], "uri": "tag:botsin.space,2017-05-13:objectId=99240:objectType=Status", "content": "<p>PINE: a small graphical system in the mother consisting of a firing raising or ability to a curms of other</p>", "url": "https://botsin.space/users/GLOSSATORY/updates/43327", "reblogs_count": 0, "favourites_count": 0, "reblog": null}