{"id": 5847697, "created_at": "2017-05-13T03:56:03.000Z", "in_reply_to_id": null, "in_reply_to_account_id": null, "sensitive": false, "spoiler_text": "", "visibility": "public", "application": null, "account": {"id": 118902, "username": "izumin", "acct": "izumin@friends.nico", "display_name": "\u3044\u305a\u307f\u3093:cat: ", "locked": false, "created_at": "2017-04-24T18:09:59.900Z", "followers_count": 0, "following_count": 0, "statuses_count": 275, "note": "<p>\u97f3MAD\u30fb\u8033\u30b3\u30d4\u30fb\u30a2\u30ec\u30f3\u30b8\u30fb\u30cb\u30b3\u751f\u30fbMHXX<br>Skype\u30fb\u30fb\u30fbizumi-rapid Discord...\u3044\u305a\u307f\u3093#3939</p>", "url": "https://friends.nico/@izumin", "avatar": "https://files.mastodon.social/accounts/avatars/000/118/902/original/4ca687ee655be081.jpg", "avatar_static": "https://files.mastodon.social/accounts/avatars/000/118/902/original/4ca687ee655be081.jpg", "header": "https://files.mastodon.social/accounts/headers/000/118/902/original/4ea1a2751bd7346e.jpg", "header_static": "https://files.mastodon.social/accounts/headers/000/118/902/original/4ea1a2751bd7346e.jpg"}, "media_attachments": [], "mentions": [], "tags": [], "uri": "tag:friends.nico,2017-05-13:objectId=8369876:objectType=Status", "content": "<p>\u901a\u79f0\u304b\u3089\u3042\u3052\u304f\u3093\uff08\u30ed\u30fc\u30bd\u30f3\u975e\u516c\u8a8d\uff09</p>", "url": "https://friends.nico/users/izumin/updates/1268613", "reblogs_count": 1, "favourites_count": 0, "reblog": null}