{
	"next_topic_id": 1,
	"topic": [],
	"topic_vote": {},
	"next_comment_id": 3,
	"comment": {
		"1_17LQPJZz9sBC1besM5ZwKFKt9CmndJTjcA": [
			{
				"comment_id": 1,
				"body": "> [vwsf](#comment_5_1MdwjTFbwpWCLfyo2ZjeXzB7DbL7euNPBi): Our current monetary SYSTEM is evil.All Jews as people are not ALL evil.Most Jews are just pawns and establishment propaganda to aim your hatred.It is the few elites, the establishment, oligarchs, nephillum, the demon possessed and oppressors WHO are evil\n\nOur system is evil. YES. But who makes it evil ?\nOnly the Jewish Talmud gives an ideological support to corrupt the system and no other religion.\nOf course the Jews are also born as innocent but their own religion and odd habits makes them different\nhttp://www.realjewnews.com/?p=156\nhttps://www.youtube.com/watch?v=Z6WwQgPl_9o&list=PLFFB05929141EE377&index=12\nhttp://www.subvertednation.net/jews-suck-baby-penises/",
				"added": 1477666547
			}
		],
		"1_125b8FxS36xSSCHkvZEhimvF5KPxjckS7o": [
			{
				"comment_id": 2,
				"body": "Jewish Joke\nQ: Why did Hitler kill himself?\nA: He got the gas bill",
				"added": 1477682756
			}
		]
	},
	"comment_vote": {}
}