{
	"next_post_id": 3,
	"next_comment_id": 1,
	"next_follow_id": 1,
	"avatar": "generate",
	"user_name": "Truthseeker",
	"hub": "1oranGeS2xsKZ4jVsu9SVttzgkYXu4k9v",
	"intro": "Random ZeroNet user",
	"post": [
		{
			"post_id": 1,
			"date_added": 1486399460,
			"body": "Hello ZeroMe!"
		},
		{
			"post_id": 1486399635,
			"body": "If anyone knows of any good and active communities here on zeronet let me know! I would love to find a replacement for HackBB that used to be on the darkent",
			"date_added": 1486399633
		}
	],
	"post_like": {},
	"comment": [],
	"follow": []
}