{
	"next_comment_id": 5,
	"user_name": "Emilie",
	"hub": "1oranGeS2xsKZ4jVsu9SVttzgkYXu4k9v",
	"post_like": {},
	"comment": [
		{
			"comment_id": 1,
			"body": "Hi! How are you ?",
			"post_uri": "1bR2k7H2rLqQ586XqYg5NEtbfcBFHqfZc_1488521503",
			"date_added": 1488554544
		},
		{
			"comment_id": 2,
			"body": "It was \"Syndicate\" on Win3.11 lol",
			"post_uri": "1EZzNxPxXMSXmEMwJSU3U8jcgjfdAeyTfr_1490386781",
			"date_added": 1490394723
		},
		{
			"comment_id": 3,
			"body": "Well job!!! Torrents are just well placed ;) No need something else! I always downloaded files with torrent, no problems! Keep it update ;)",
			"post_uri": "1NAaF8VitwKSPo79RzJFhqz14gndmdWcGV_1490394361",
			"date_added": 1490395119
		},
		{
			"comment_id": 4,
			"body": "Hi ! How are you?",
			"post_uri": "14SJVayd4F6hQZ2yxZpNSn1hTh9tdZgJrj_1",
			"date_added": 1491637989
		}
	]
}