{
	"next_topic_id": 1,
	"topic": [],
	"topic_vote": {},
	"next_comment_id": 3,
	"comment": {
		"5_1PTaJe3LLeB5Pfxq8KjcpQSPcSK1PQqsQs": [
			{
				"comment_id": 1,
				"body": "A site which gathers all the revolution vidéo footage to make us aware of whats happening in the world second by second ! And If someone know such an adress let us know ! fR",
				"added": 1487264243
			},
			{
				"comment_id": 2,
				"body": "> [burningcold](#comment_14_1PTaJe3LLeB5Pfxq8KjcpQSPcSK1PQqsQs): Video content can't be served on ZeroNet. It does not work with the model. However, there's no reason that ZeroNet pages can't link to/embed video content served on other networks, either legacy Internet or neonets like IPFS.\n\nYep that would be nice, it would be an invisible link between Zeronet and centralized internet. You could create false doors inside dem www with IPFS standard mode tri IP adress, and then open link to invisible Https site ! Wouldn't it be great ?",
				"added": 1487273442
			}
		]
	},
	"comment_vote": {
		"1_14Jg9Gfa7bt5TgqR3LPoPVRQAyvxYhjFtE": 1,
		"14_1PTaJe3LLeB5Pfxq8KjcpQSPcSK1PQqsQs": 1,
		"2_14Jg9Gfa7bt5TgqR3LPoPVRQAyvxYhjFtE": 1
	}
}