{
	"next_comment_id": 4,
	"comment": [
		{
			"comment_id": 1,
			"body": "why ？？\" Your network connection is restricted. Please, open 15441 port\non your router to make your site accessible for everyone. \",I don't have a router.。。。。。。",
			"post_id": 3,
			"date_added": 1462599513
		},
		{
			"comment_id": 2,
			"body": "> [niuniu](#comment_1_1Q88bcGjfY3qbAg5DX8xKHYtEzLzijfRgH): 哥们儿，你是传说中的zeronet的作者？\n\nThe author's zeroname is nofish，he maybe can't understand Chinese.^__^",
			"post_id": 95,
			"date_added": 1476543411
		},
		{
			"comment_id": 3,
			"body": "Good Job，Man",
			"post_id": 96,
			"date_added": 1478653480
		}
	],
	"comment_vote": {},
	"topic_vote": {},
	"post_vote": {
		"96": 1
	}
}