{
	"next_post_id": 3,
	"next_comment_id": 2,
	"next_follow_id": 2,
	"avatar": "generate",
	"user_name": "Being2013",
	"hub": "1oranGeS2xsKZ4jVsu9SVttzgkYXu4k9v",
	"intro": "新 ZeroNet 用户",
	"post": [
		{
			"post_id": 1,
			"date_added": 1485081734,
			"body": "你好 ZeroMe!"
		},
		{
			"post_id": 1485081752,
			"body": "大家好",
			"date_added": 1485081750
		}
	],
	"post_like": {},
	"comment": [
		{
			"comment_id": 1,
			"body": "@Zeronetapk: 新手，能推荐点站点吗？\n",
			"post_uri": "1BhPLnre5wD81uEWtjdp7Ggk1Fmu5o6qaE_1485081752",
			"date_added": 1485089273
		}
	],
	"follow": [
		{
			"follow_id": 1,
			"hub": "1GrEenUGRWnzaNZjR3XsQa6dQgdPDTyt7i",
			"auth_address": "13YuSFL3YKh6KQPWAgxtfiufGMTDHypVFM",
			"user_name": "怡红院",
			"date_added": 1485085290
		}
	]
}